nautilus-registry/__init__.py
nautilus-registry/util.py
nautilus-registry/fields/__init__.py
nautilus-registry/fields/connections/__init__.py
nautilus-registry/fields/connections/async.py
nautilus-registry/fields/connections/base.py
nautilus-registry/fields/connections/sync.py
nautilus-registry/objectTypes/__init__.py
nautilus-registry/objectTypes/serviceObjectType.py
nautilus-registry/registry/__init__.py
nautilus_registry/__init__.py
nautilus_registry/registry.py
nautilus_registry/service.py
nautilus_registry/util.py
nautilus_registry/api/__init__.py
nautilus_registry/api/fields/__init__.py
nautilus_registry/api/fields/connections/__init__.py
nautilus_registry/api/fields/connections/async.py
nautilus_registry/api/fields/connections/base.py
nautilus_registry/api/fields/connections/sync.py
nautilus_registry/api/objectTypes/__init__.py
nautilus_registry/api/objectTypes/serviceObjectType.py
nautilus_registry-0.1.7.dist-info/DESCRIPTION.rst
nautilus_registry-0.1.7.dist-info/METADATA
nautilus_registry-0.1.7.dist-info/RECORD
nautilus_registry-0.1.7.dist-info/WHEEL
nautilus_registry-0.1.7.dist-info/entry_points.txt
nautilus_registry-0.1.7.dist-info/metadata.json
nautilus_registry-0.1.7.dist-info/top_level.txt
