Metadata-Version: 2.0
Name: nautilus-registry
Version: 0.1.7
Summary: A module for powering a nautilus application with a service registry.
Home-page: https://github.com/AlecAivazis/nautilus-registry
Author: Alec Aivazis
Author-email: alec@aivazis.com
License: UNKNOWN
Download-URL: https://github.com/aaivazis/nautilus-registry/tarball/0.1.0
Keywords: microservice,asyncio,graphql
Platform: UNKNOWN
Requires-Dist: graphene
Requires-Dist: nautilus
Requires-Dist: python-consul
Requires-Dist: requests
